rfb_shared_tool/__init__.py
rfb_shared_tool/__version__.py
rfb_shared_tool/context.py
rfb_shared_tool/sys_shd_channels.py
rfb_shared_tool/sys_shd_common.py
rfb_shared_tool/sys_shd_objects.py
rfb_shared_tool-0.0.6.dist-info/LICENSE.txt
rfb_shared_tool-0.0.6.dist-info/METADATA
rfb_shared_tool-0.0.6.dist-info/WHEEL
rfb_shared_tool-0.0.6.dist-info/top_level.txt
rfb_shared_tool-0.0.6.dist-info/RECORD
