Metadata-Version: 2.1
Name: rfb_shared_tool
Version: 0.0.6
Summary: Toolchain used for Inter Process Communication (IPC) on python platform.
Author-email: Raldea <r.aldea.csic+pypi@gmail.com>, Javier Sanz <javiersanzmoline@gmail.com>, Luis Roche <luis.roche@hotmail.com>, Marius Crisan <mariuscrsn+pypi@gmail.com>, Pablo Pastor <pastorpflores+pypi@gmail.com>
Maintainer-email: Javier Sanz <javiersanzmoline@gmail.com>, Raldea <r.aldea.csic+pypi@gmail.com>
License: GNU GENERAL PUBLIC LICENSE
Project-URL: Homepage, https://github.com/GIDEF-RFB/System-Tools
Project-URL: Bug Reports, https://github.com/GIDEF-RFB/System-Tools/issues
Project-URL: Bug Tracker, https://github.com/GIDEF-RFB/Battery-Cycler-Drivers/issues
Project-URL: Source, https://github.com/GIDEF-RFB/System-Tools/code/sys_shd
Project-URL: Funding, https://donate.pypi.org
Keywords: yaml,configuration,synchronization,IPC,channel message,queue,multithreading,concurrency,parallel,messaging
Classifier: Development Status :: 3 - Alpha
Classifier: Topic :: Software Development :: Embedded Systems
Classifier: Operating System :: OS Independent
Classifier: License :: OSI Approved :: GNU Affero General Public License v3
Classifier: Programming Language :: Python :: 3
Classifier: Programming Language :: Python :: 3.7
Classifier: Programming Language :: Python :: 3.8
Classifier: Programming Language :: Python :: 3.9
Classifier: Programming Language :: Python :: 3.10
Classifier: Programming Language :: Python :: 3.11
Classifier: Programming Language :: Python :: 3 :: Only
Requires-Python: >=3.7
License-File: LICENSE.txt
Requires-Dist: ipcqueue
Requires-Dist: PyYAML >=6.0.1
Requires-Dist: rfb-config-tool >=0.0.1
Requires-Dist: rfb-logger-tool >=0.0.1
